neuronos_capabilities/__init__.py
neuronos_capabilities/__version__.py
neuronos_capabilities/SQLManager/__init__.py
neuronos_capabilities/SQLManager/artifact.yaml
neuronos_capabilities/SQLManager/sql_manager.py
neuronos_capabilities/SQLManager/adapters/__init__.py
neuronos_capabilities/SQLManager/adapters/postgres_adapter.py
neuronos_capabilities/SQLManager/config/__init__.py
neuronos_capabilities/SQLManager/config/sql_config.py
neuronos_capabilities/SQLManager/examples/testing_library_execution.py
neuronos_capabilities/SQLManager/exceptions/__init__.py
neuronos_capabilities/SQLManager/exceptions/sql_exceptions.py
neuronos_capabilities/SQLManager/migrations/__init__.py
neuronos_capabilities/SQLManager/migrations/alembic_manager.py
neuronos_capabilities/SQLManager/models/__init__.py
neuronos_capabilities/SQLManager/models/base.py
neuronos_capabilities/SQLManager/ports/__init__.py
neuronos_capabilities/SQLManager/ports/sql_port.py
neuronos_capabilities/SQLManager/tests/__init__.py
neuronos_capabilities/SQLManager/utils/__init__.py
neuronos_capabilities/SQLManager/utils/query_builder.py
neuronos_capabilities/SQLManager/utils/singleton.py
neuronos_capabilities-0.0.1.dist-info/LICENSE
neuronos_capabilities-0.0.1.dist-info/METADATA
neuronos_capabilities-0.0.1.dist-info/WHEEL
neuronos_capabilities-0.0.1.dist-info/top_level.txt
neuronos_capabilities-0.0.1.dist-info/RECORD
