Metadata-Version: 2.1
Name: neuronos-capabilities
Version: 0.0.1
Summary: NeuronOS Python Capabilities Library - Provider-agnostic backend capabilities following hexagonal architecture
Author-email: NeuronOS <tech@neuron-studios.com>
Project-URL: Homepage, https://github.com/neuronos/neuronos_python_capabilities_library
Project-URL: Repository, https://github.com/neuronos/neuronos_python_capabilities_library
Keywords: neuronos,capabilities,hexagonal-architecture,sqlmanager
Classifier: Development Status :: 4 - Beta
Classifier: Intended Audience :: Developers
Classifier: Programming Language :: Python :: 3
Classifier: Operating System :: OS Independent
Requires-Python: >=3.9
License-File: LICENSE
Requires-Dist: sqlalchemy<3.0.0,>=2.0.23
Requires-Dist: psycopg2-binary<3.0.0,>=2.9.9
Requires-Dist: asyncpg<1.0.0,>=0.29.0
Requires-Dist: alembic<2.0.0,>=1.13.1
Requires-Dist: typing-extensions>=4.9.0
Provides-Extra: dev
Requires-Dist: pytest>=7.4.3; extra == "dev"
Requires-Dist: pytest-asyncio>=0.21.1; extra == "dev"
Requires-Dist: pytest-cov>=4.1.0; extra == "dev"
Requires-Dist: twine>=5.1.1; extra == "dev"
Requires-Dist: build>=1.0.0; extra == "dev"
